vpp_vrouter/__init__.py
vpp_vrouter/client/__init__.py
vpp_vrouter/client/client.py
vpp_vrouter/client/config.sh
vpp_vrouter/client/examples.py
vpp_vrouter/client/ubuntu1.py
vpp_vrouter/client/ubuntu2.py
vpp_vrouter/common/__init__.py
vpp_vrouter/common/custom_marshmallow_fields.py
vpp_vrouter/common/models.py
vpp_vrouter/common/serializers.py
vpp_vrouter/common/utils.py
vpp_vrouter/frr/__init__.py
vpp_vrouter/frr/agent.py
vpp_vrouter/frr/route_reflector.py
vpp_vrouter/server/__init__.py
vpp_vrouter/server/handlers.py
vpp_vrouter/server/pyro.py
vpp_vrouter/server/server.py
vpp_vrouter/tests/__init__.py
vpp_vrouter/tests/test.py
vpp_vrouter-0.1.29.dist-info/LICENSE
vpp_vrouter-0.1.29.dist-info/METADATA
vpp_vrouter-0.1.29.dist-info/WHEEL
vpp_vrouter-0.1.29.dist-info/entry_points.txt
vpp_vrouter-0.1.29.dist-info/RECORD
