Metadata-Version: 2.1
Name: vpp-vrouter
Version: 0.1.29
Summary: USDN vRouter with VPP
License: US Data Networks. All rights reserved.
Author: Filip Gschwandtner
Author-email: filip.gschwandtner@pantheon.tech
Requires-Python: >=3.10,<4.0
Classifier: License :: Other/Proprietary License
Classifier: Programming Language :: Python :: 3
Classifier: Programming Language :: Python :: 3.10
Classifier: Programming Language :: Python :: 3.11
Requires-Dist: Pyro5 (>=5.15,<6.0)
Requires-Dist: dataclasses-json (>=0.5.7,<0.6.0)
Requires-Dist: jsonrpclib (>=0.2.1,<0.3.0)
Requires-Dist: marshmallow (>=3.20.0,<4.0.0)
Requires-Dist: marshmallow-dataclass (>=8.6.0,<9.0.0)
Requires-Dist: marshmallow-enum (>=1.5.1,<2.0.0)
Requires-Dist: mypy-extensions (>=1.0.0,<2.0.0)
Requires-Dist: numpy (>=1.26.0,<2.0.0)
Requires-Dist: packaging (>=24.0,<25.0)
Requires-Dist: pyroute2 (>=0.8.0,<0.9.0)
Requires-Dist: python-json-logger (>=3.0.0,<4.0.0)
Requires-Dist: serpent (>=1.41,<2.0)
Requires-Dist: sudo (>=1.0.0,<2.0.0)
Requires-Dist: typing-extensions (>=4.15.0,<5.0.0)
Requires-Dist: typing-inspect (>=0.9.0,<0.10.0)
Requires-Dist: vpp-papi (>=2.3.0,<3.0.0)
